omniblack/secret.abi3.so
omniblack.secret-0.0.11.dist-info/LICENSE
omniblack.secret-0.0.11.dist-info/METADATA
omniblack.secret-0.0.11.dist-info/WHEEL
omniblack.secret-0.0.11.dist-info/omniblack_package.json
omniblack.secret-0.0.11.dist-info/top_level.txt
omniblack.secret-0.0.11.dist-info/RECORD
