Metadata-Version: 2.1
Name: omniblack.secret
Version: 0.0.11
Author-email: Terry Patterson <terryp@wegrok.net>
License: MIT License
Project-URL: Homepage, https://gitlab.com/terryp/secret
Project-URL: Repository, https://gitlab.com/terryp/secret.git
Classifier: Development Status :: 3 - Alpha
Classifier: Intended Audience :: Developers
Classifier: License :: OSI Approved :: MIT License
Classifier: Operating System :: POSIX :: Linux
Classifier: Programming Language :: Python :: 3
Classifier: Programming Language :: Python :: 3.12
Classifier: Programming Language :: Python :: Implementation :: CPython
Classifier: Topic :: Security
Classifier: Topic :: Software Development
Requires-Python: >=3.12
License-File: LICENSE
Provides-Extra: test
Requires-Dist: pytest ; extra == 'test'
